yuuz12_sdk-0.1.5.dist-info/METADATA
yuuz12_sdk-0.1.5.dist-info/WHEEL
yuuz12_sdk/__init__.py
yuuz12_sdk/apis/__init__.py
yuuz12_sdk/apis/_api.py
yuuz12_sdk/apis/baidu.py
yuuz12_sdk/apis/baidu.pyi
yuuz12_sdk/apis/bangumi.py
yuuz12_sdk/apis/bangumi.pyi
yuuz12_sdk/apis/cave.py
yuuz12_sdk/apis/cave.pyi
yuuz12_sdk/apis/email.py
yuuz12_sdk/apis/email.pyi
yuuz12_sdk/apis/invitation.py
yuuz12_sdk/apis/invitation.pyi
yuuz12_sdk/apis/minecraft.py
yuuz12_sdk/apis/minecraft.pyi
yuuz12_sdk/apis/prize.py
yuuz12_sdk/apis/prize.pyi
yuuz12_sdk/apis/statistics.py
yuuz12_sdk/apis/statistics.pyi
yuuz12_sdk/apis/user.py
yuuz12_sdk/apis/user.pyi
yuuz12_sdk/exceptions.py
yuuz12_sdk/log.py
yuuz12_sdk/models/__init__.py
yuuz12_sdk/models/user.py
yuuz12_sdk-0.1.5.dist-info/RECORD
