Metadata-Version: 2.1
Name: yuuz12-sdk
Version: 0.1.5
Summary: Python 3 SDK for Yuuz12-Api. Check https://doc.yuuz12.top/web/#/5/ 
Keywords: yuuz12,shiruku
Author-Email: Number_Sir <number_sir@126.com>
Maintainer-Email: Number_Sir <number_sir@126.com>
License: MIT
Project-URL: Repository, https://github.com/NumberSir/yuuz12-sdk
Project-URL: Issues, https://github.com/NumberSir/yuuz12-sdk/issues
Requires-Python: >=3.11
Requires-Dist: loguru>=0.7.2
Requires-Dist: python-dotenv>=1.0.1
Requires-Dist: httpx>=0.27.0
